mcp_tinybird/__init__.py
mcp_tinybird/__main__.py
mcp_tinybird/run_sse.py
mcp_tinybird/run_stdio.py
mcp_tinybird/server.py
mcp_tinybird/sse.py
mcp_tinybird/stdio.py
mcp_tinybird/tb.py
mseep_mcp_tinybird-1.0.6.dist-info/licenses/LICENSE
mseep_mcp_tinybird-1.0.6.dist-info/METADATA
mseep_mcp_tinybird-1.0.6.dist-info/WHEEL
mseep_mcp_tinybird-1.0.6.dist-info/entry_points.txt
mseep_mcp_tinybird-1.0.6.dist-info/top_level.txt
mseep_mcp_tinybird-1.0.6.dist-info/RECORD
