Metadata-Version: 2.4
Name: mseep-mcp-tinybird
Version: 1.0.6
Summary: An MCP server to interact with a Tinybird Workspace from any MCP client.
Author-email: mseep <support@skydeck.ai>
Project-URL: homepage, https://github.com/tinybirdco/mcp-tinybird
Requires-Python: >=3.10
License-File: LICENSE
Requires-Dist: httpx>=0.27.2
Requires-Dist: mcp>=1.0.0
Requires-Dist: python-dotenv>=1.0.1
Requires-Dist: tinybird-python-sdk>=0.1.6
Requires-Dist: uvicorn>=0.27.0
Requires-Dist: starlette>=0.36.0
Provides-Extra: dev
Requires-Dist: black>=23.12.1; extra == "dev"
Requires-Dist: pyproject-toml>=0.0.10; extra == "dev"
Dynamic: license-file
